Metadata-Version: 2.1
Name: digests
Version: 0.0.3
Summary: Tools for news corpora
Home-page: http://github.com/interrogator/digests
Author: Danny McDonald
Author-email: mcddjx@gmail.com
License: MIT
Platform: UNKNOWN
